Metadata-Version: 1.1
Name: pyMicVoiceDetection
Version: 2.1.0
Summary: easy Voice Activitive Dectection from MIC for python
Home-page: https://pypi.org/project/pyMicVoiceDetection
Author: KuoYuan Li
Author-email: funny4875@gmail.com
License: UNKNOWN
Keywords: Voice Activitive Detection,VAD,MicVoiceDetection
Platform: UNKNOWN
Classifier: License :: OSI Approved :: MIT License
Classifier: Programming Language :: Python :: 3.6
Classifier: Programming Language :: Python :: 3.7
Classifier: Programming Language :: Python :: 3.8
